got10k/__init__.py
got10k/datasets/__init__.py
got10k/datasets/dtb70.py
got10k/datasets/got10k.py
got10k/datasets/nfs.py
got10k/datasets/otb.py
got10k/datasets/tcolor128.py
got10k/datasets/uav123.json
got10k/datasets/uav123.py
got10k/datasets/vid.py
got10k/datasets/vot.py
got10k/experiments/__init__.py
got10k/experiments/dtb70.py
got10k/experiments/got10k.py
got10k/experiments/nfs.py
got10k/experiments/otb.py
got10k/experiments/tcolor128.py
got10k/experiments/uav123.py
got10k/experiments/vot.py
got10k/trackers/__init__.py
got10k/trackers/identity_tracker.py
got10k/utils/__init__.py
got10k/utils/ioutils.py
got10k/utils/metrics.py
got10k/utils/viz.py
got10k-0.1.2.dist-info/LICENSE
got10k-0.1.2.dist-info/METADATA
got10k-0.1.2.dist-info/WHEEL
got10k-0.1.2.dist-info/top_level.txt
got10k-0.1.2.dist-info/RECORD
