Metadata-Version: 2.1
Name: got10k
Version: 0.1.2
Summary: GOT-10k benchmark official API
Home-page: https://github.com/got-10k/toolkit
Author: Lianghua Huang
Author-email: lianghua.huang.cs@gmail.com
License: MIT
Keywords: GOT-10k,Generic Object Tracking,Benchmark
Platform: UNKNOWN
Requires-Dist: numpy
Requires-Dist: matplotlib
Requires-Dist: Pillow
Requires-Dist: Shapely
Requires-Dist: fire
